{
    "OtherFleet": "Une flotte au départ de %1$s s'approche de %2$s avec comme ordre : %3$s",
    "Spy": "Espionner",
    "NoMove": "Aucun mouvement de flottes détecté",
    "End": "Fin",
    "OtherFleets": "Autres troupes",
    "YourFleet": "Votre flotte en partance de %1$s se dirige vers %2$s avec comme ordre : %3$s",
    "MoveNumber:": "Nombre de mouvement :",
    "Base": "Baser",
    "Back": "Retour",
    "Attack": "Attaquer",
    "UnitsMove": "Mouvement de flottes",
    "YourFleets": "Vos troupes",
    "CommandCenter": "Centre de commandement",
    "BackFleet": "Votre flotte de retour de %1$s se dirige vers %2$s",
    "Time": "Temps",
    "Cancel": "Annuler",
    "Colon": "Coloniser",
    "Port": "Transporter"
}