{
    "id_10_name": "Blindage élargi du vaisseau",
    "id_6_name": "Technique d'éspionnage",
    "id_9_description": "Technique de camouflage",
    "id_5_name": "Capacité de charge augmentée",
    "id_7_name": "Propulsion spatio-temporelle",
    "id_11_description": "Technique de bouclier",
    "id_2_name": "Propulsion à ions",
    "id_8_description": "Technique de capteur",
    "id_12_name": "Alignement d'énergie",
    "id_13_description": "Ionisation",
    "id_4_name": "Technique de colonisation",
    "id_3_description": "Propulsion hyperespace",
    "id_13_name": "Ionisation",
    "id_16_description": "Diplomatie",
    "id_2_description": "Propulsion à ions",
    "id_1_description": "Propulsion à combustion interne",
    "id_6_description": "Technique d'éspionnage",
    "id_1_name": "Propulsion à combustion interne",
    "id_12_description": "Alignement d'énergie",
    "id_14_description": "Projectiles explosifs",
    "id_8_name": "Technique de capteur",
    "id_5_description": "Capacité de charge augmentée",
    "id_15_description": "Projectile de plasma",
    "id_15_name": "Projectile de plasma",
    "id_3_name": "Propulsion hyperespace",
    "id_4_description": "Technique de colonisation",
    "id_16_name": "Diplomatie",
    "id_14_name": "Projectiles explosifs",
    "id_11_name": "Technique de bouclier",
    "id_7_description": "Propulsion spatio-temporelle",
    "id_9_name": "Technique de camouflage",
    "id_10_description": "Blindage élargi du vaisseau"
}