{
    "id_6_description": "Corvette",
    "id_22_description": "Tour. à laser lourd",
    "id_24_name": "Canon antimatière",
    "id_25_description": "Batterie nucléaire de lance-missile nanobot antimatière",
    "id_9_description": "Destroyer",
    "id_5_name": "Satellite espion",
    "id_7_name": "Croiseur",
    "id_11_description": "Vaisseau de commerce",
    "id_2_name": "Chasseur lourd",
    "id_8_description": "Esperanza",
    "id_12_name": "Transporteur",
    "id_25_name": "BNLMNA",
    "id_3_name": "Exo-chasseur",
    "id_4_name": "Serenity",
    "id_24_description": "Canon antimatière",
    "id_6_name": "Corvette",
    "id_3_description": "Exo-chasseur",
    "id_19_description": "Colonisateur",
    "id_16_description": "Serenity SR6",
    "id_22_name": "Tour. à laser lourd",
    "id_2_description": "Chasseur lourd",
    "id_1_description": "Chasseur léger",
    "id_10_name": "Leviathan",
    "id_1_name": "Chasseur léger",
    "id_12_description": "Transporteur",
    "id_23_description": "Canon à ion",
    "id_14_description": "Behemoth",
    "id_8_name": "Esperanza",
    "id_5_description": "Satellite espion",
    "id_21_description": "Tour. à laser léger",
    "id_15_description": "Aurora",
    "id_23_name": "Canon à ion",
    "id_15_name": "Aurora",
    "id_21_name": "Tour. à laser léger",
    "id_19_name": "Colonisateur",
    "id_4_description": "Serenity",
    "id_16_name": "Serenity SR6",
    "id_14_name": "Behemoth",
    "id_11_name": "Vaisseau de commerce",
    "id_7_description": "Croiseur",
    "id_9_name": "Destroyer",
    "id_10_description": "Leviathan"
}