{
    "OtherFleet": "Flota z %1$s zmierza do %2$s z rozkazem: %3$s",
    "Spy": "Szpieguj",
    "NoMove": "Nie wykryto żadnych flot",
    "End": "Koniec",
    "OtherFleets": "Pozostałe floty",
    "YourFleet": "Twoja flota z %1$s zmierza do %2$s z rozkazem: %3$s",
    "MoveNumber:": "Liczba flot:",
    "Base": "Stacjonuj",
    "Back": "Powrót",
    "Attack": "Atak",
    "UnitsMove": "Floty",
    "YourFleets": "Twoje floty",
    "CommandCenter": "Centrum dowodzenia",
    "BackFleet": "Twoja flota wraca z %1$s zmierza do %2$s",
    "Time": "Czas",
    "Cancel": "Anuluj",
    "Colon": "Kolonizuj",
    "Port": "Transport"
}